hpinterp/InterpMap.py
hpinterp/__init__.py
hpinterp-0.1.2.dist-info/METADATA
hpinterp-0.1.2.dist-info/LICENSE
hpinterp-0.1.2.dist-info/WHEEL
hpinterp-0.1.2.dist-info/RECORD
